provbug/FunctionActivation.py
provbug/VariableState.py
provbug/__main__.py
provbug/provbug.py
provbug-0.2.3.data/scripts/FunctionActivation.py
provbug-0.2.3.data/scripts/VariableState.py
provbug-0.2.3.data/scripts/__main__.py
provbug-0.2.3.data/scripts/provbug.py
provbug-0.2.3.dist-info/METADATA
provbug-0.2.3.dist-info/RECORD
provbug-0.2.3.dist-info/WHEEL
provbug-0.2.3.dist-info/entry_points.txt
provbug-0.2.3.dist-info/top_level.txt
