Metadata-Version: 2.1
Name: provbug
Version: 0.2.3
Summary: Supporting infrastructure to debug scientific experiments with noworkflow
Home-page: https://github.com/linharesh/provbug
Author: Henrique Linhares, and Rômulo Ponciano
Author-email: hlinhares@id.uff.br
License: UNKNOWN
Keywords: scientific,experiments,provenance,debug
Platform: UNKNOWN
Classifier: Development Status :: 3 - Alpha
Classifier: License :: OSI Approved :: MIT License
Classifier: Programming Language :: Python :: 3.5
Classifier: Programming Language :: Python :: 3.6
Requires-Python: >=3.5
